ewmhlib/Props.py
ewmhlib/Structs.py
ewmhlib/__init__.py
ewmhlib/_ewmhlib.py
ewmhlib/_main.py
ewmhlib/_props.py
ewmhlib/_structs.py
ewmhlib/py.typed
ewmhlib/Props/__init__.py
ewmhlib/Props/_props.py
ewmhlib/Structs/__init__.py
ewmhlib/Structs/_structs.py
EWMHlib-0.1.dist-info/AUTHORS.txt
EWMHlib-0.1.dist-info/LICENSE.txt
EWMHlib-0.1.dist-info/METADATA
EWMHlib-0.1.dist-info/WHEEL
EWMHlib-0.1.dist-info/top_level.txt
EWMHlib-0.1.dist-info/RECORD
