Metadata-Version: 2.1
Name: EWMHlib
Version: 0.1
Summary: Extended Window Manager Hints implementation in Python 3
Home-page: https://github.com/Kalmat/EWMHlib
Author: Kalmat
Author-email: palookjones@gmail.com
License: BSD 3
Keywords: ewmh Extended-Window-manager-hints window-manager window manager hints
Classifier: Development Status :: 4 - Beta
Classifier: Environment :: X11 Applications
Classifier: Intended Audience :: Developers
Classifier: License :: OSI Approved :: BSD License
Classifier: Operating System :: OS Independent
Classifier: Programming Language :: Python
Classifier: Programming Language :: Python :: 3
Classifier: Programming Language :: Python :: 3 :: Only
Classifier: Programming Language :: Python :: 3.9
Classifier: Programming Language :: Python :: 3.10
Classifier: Programming Language :: Python :: 3.11
License-File: LICENSE.txt
License-File: AUTHORS.txt
Requires-Dist: typing-extensions >=4.4.0
Requires-Dist: python-xlib >=0.21 ; sys_platform == "linux"
Provides-Extra: dev
Requires-Dist: types-setuptools >=65.5 ; extra == 'dev'
Requires-Dist: mypy >=0.990 ; extra == 'dev'
Requires-Dist: types-python-xlib >=0.32 ; extra == 'dev'
